simple_pypi_template/__init__.py
simple_pypi_template/simple_pypi_template.py
simple_pypi_template/submodule.py
simple_pypi_template-1.0.1.dist-info/LICENSE
simple_pypi_template-1.0.1.dist-info/METADATA
simple_pypi_template-1.0.1.dist-info/WHEEL
simple_pypi_template-1.0.1.dist-info/top_level.txt
simple_pypi_template-1.0.1.dist-info/RECORD
