Metadata-Version: 2.1
Name: simple-pypi-template
Version: 1.0.1
Summary: Template and instructions to create a Python module and upload to PyPI
Home-page: https://github.com/Invarato/simple_pypi_template_project
Author: Ramón Invarato Menéndez
Author-email: r.invarato@gmail.com
License: UNKNOWN
Platform: UNKNOWN
Classifier: Programming Language :: Python :: 3
Classifier: License :: OSI Approved :: MIT License
Classifier: Operating System :: OS Independent
Requires-Python: >=3.0
